[
  {
    "pangalan": "Abe",
    "adjscore": "98",
    "forfedex": "*",
    "hdcp": "22",
    "net": "76"
  },
  {
    "pangalan": "Abner",
    "adjscore": "82",
    "forfedex": "*",
    "hdcp": "8",
    "net": "74"
  },
  {
    "pangalan": "Boyet",
    "adjscore": "-",
    "forfedex": "",
    "hdcp": "21",
    "net": "-"
  },
  {
    "pangalan": "Jim",
    "adjscore": "-",
    "forfedex": "",
    "hdcp": "16",
    "net": "-"
  },
  {
    "pangalan": "Jon",
    "adjscore": "-",
    "forfedex": "",
    "hdcp": "12",
    "net": "-"
  },
  {
    "pangalan": "Lito",
    "adjscore": "87",
    "forfedex": "*",
    "hdcp": "13",
    "net": "74"
  },
  {
    "pangalan": "Mel",
    "adjscore": "96",
    "forfedex": "*",
    "hdcp": "20",
    "net": "76"
  },
  {
    "pangalan": "Nes",
    "adjscore": "-",
    "forfedex": "",
    "hdcp": "13",
    "net": "-"
  },
  {
    "pangalan": "Tom",
    "adjscore": "-",
    "forfedex": "",
    "hdcp": "11",
    "net": "-"
  },
  {
    "pangalan": "Tony",
    "adjscore": "84",
    "forfedex": "*",
    "hdcp": "14",
    "net": "70"
  },
  {
    "pangalan": "Vedel",
    "adjscore": "93",
    "forfedex": "*",
    "hdcp": "14",
    "net": "79"
  }
]